scrapix/__init__.py
scrapix/api_client.py
scrapix/api_response.py
scrapix/configuration.py
scrapix/exceptions.py
scrapix/py.typed
scrapix/rest.py
scrapix/api/__init__.py
scrapix/api/api_services_api.py
scrapix/api/default_api.py
scrapix/models/__init__.py
scrapix/models/collect_input.py
scrapix/models/collect_result.py
scrapix/models/crawl_input.py
scrapix/models/crawl_result.py
scrapix/models/data1.py
scrapix/models/extract_input.py
scrapix/models/extract_result.py
scrapix/models/http_validation_error.py
scrapix/models/output_format.py
scrapix/models/scrape_input.py
scrapix/models/scrape_result.py
scrapix/models/structured_output.py
scrapix/models/structured_output_format.py
scrapix/models/structured_output_schema.py
scrapix/models/summarize_schema.py
scrapix/models/validation_error.py
scrapix/models/validation_error_loc_inner.py
scrapix-0.1.2.dist-info/METADATA
scrapix-0.1.2.dist-info/WHEEL
scrapix-0.1.2.dist-info/RECORD
