Metadata-Version: 2.4
Name: scrapix
Version: 0.1.2
Summary: Scrapix
Project-URL: Repository, https://scrapix.promptcloud.com
Author-email: PromptCloud <sales@promptcloud.com>
Keywords: FastAPI,OpenAPI,OpenAPI-Generator,Scraper,Scrapix
Requires-Python: >=3.9
Requires-Dist: pydantic>=2
Requires-Dist: python-dateutil>=2.8.2
Requires-Dist: typing-extensions>=4.7.1
Requires-Dist: urllib3<3.0.0,>=2.1.0
Provides-Extra: dev
Requires-Dist: pytest; extra == 'dev'
Requires-Dist: ruff; extra == 'dev'
